pure_eval/__init__.py
pure_eval/core.py
pure_eval/my_getattr_static.py
pure_eval/utils.py
pure_eval/version.py
pure_eval-0.2.1.dist-info/LICENSE.txt
pure_eval-0.2.1.dist-info/METADATA
pure_eval-0.2.1.dist-info/WHEEL
pure_eval-0.2.1.dist-info/top_level.txt
pure_eval-0.2.1.dist-info/RECORD
